{"otherData": {},"traceEvents":[{"cat":"function","dur":42424,"name":"void __cdecl Debut::OpenGLContext::Init(void)","ph":"X","pid":0,"tid":2665228401,"ts":254137917182},{"cat":"function","dur":92,"name":"void __cdecl Debut::WindowsWindow::SetVSync(bool)","ph":"X","pid":0,"tid":2665228401,"ts":254137959891},{"cat":"function","dur":718531,"name":"void __cdecl Debut::WindowsWindow::Init(const struct Debut::WindowProps &)","ph":"X","pid":0,"tid":2665228401,"ts":254137241592},{"cat":"function","dur":63,"name":"__cdecl Debut::OpenGLVertexArray::OpenGLVertexArray(void)","ph":"X","pid":0,"tid":2665228401,"ts":254137960337},{"cat":"function","dur":134,"name":"__cdecl Debut::OpenGLIndexBuffer::OpenGLIndexBuffer(int *,unsigned int)","ph":"X","pid":0,"tid":2665228401,"ts":254137960781},{"cat":"function","dur":853,"name":"__cdecl Debut::OpenGLVertexBuffer::OpenGLVertexBuffer(unsigned int)","ph":"X","pid":0,"tid":2665228401,"ts":254137961038},{"cat":"function","dur":57,"name":"__cdecl Debut::OpenGLVertexArray::OpenGLVertexArray(void)","ph":"X","pid":0,"tid":2665228401,"ts":254137962015},{"cat":"function","dur":2,"name":"void __cdecl Debut::OpenGLVertexBuffer::Bind(void) const","ph":"X","pid":0,"tid":2665228401,"ts":254137962295},{"cat":"function","dur":0,"name":"void __cdecl Debut::OpenGLIndexBuffer::Bind(void) const","ph":"X","pid":0,"tid":2665228401,"ts":254137962439},{"cat":"function","dur":138,"name":"__cdecl Debut::OpenGLTexture2D::OpenGLTexture2D(unsigned int,unsigned int)","ph":"X","pid":0,"tid":2665228401,"ts":254137964457},{"cat":"function","dur":22,"name":"void __cdecl Debut::OpenGLTexture2D::SetData(void *,unsigned int)","ph":"X","pid":0,"tid":2665228401,"ts":254137964715},{"cat":"function","dur":258,"name":"class std::basic_string<char,struct std::char_traits<char>,class std::allocator<char> > __cdecl Debut::OpenGLShader::ReadFile(const class std::basic_string<char,struct std::char_traits<char>,class std::allocator<char> > &)","ph":"X","pid":0,"tid":2665228401,"ts":254137964853},{"cat":"function","dur":85,"name":"class std::unordered_map<unsigned int,class std::basic_string<char,struct std::char_traits<char>,class std::allocator<char> >,struct std::hash<unsigned int>,struct std::equal_to<unsigned int>,class std::allocator<struct std::pair<unsigned int const ,class std::basic_string<char,struct std::char_traits<char>,class std::allocator<char> > > > > __cdecl Debut::OpenGLShader::PreProcess(const class std::basic_string<char,struct std::char_traits<char>,class std::allocator<char> > &)","ph":"X","pid":0,"tid":2665228401,"ts":254137965177},{"cat":"function","dur":833,"name":"void __cdecl Debut::OpenGLShader::Compile(class std::unordered_map<unsigned int,class std::basic_string<char,struct std::char_traits<char>,class std::allocator<char> >,struct std::hash<unsigned int>,struct std::equal_to<unsigned int>,class std::allocator<struct std::pair<unsigned int const ,class std::basic_string<char,struct std::char_traits<char>,class std::allocator<char> > > > > &)","ph":"X","pid":0,"tid":2665228401,"ts":254137965324},{"cat":"function","dur":474,"name":"void __cdecl Debut::OpenGLShader::Link(void)","ph":"X","pid":0,"tid":2665228401,"ts":254137966264},{"cat":"function","dur":1982,"name":"__cdecl Debut::OpenGLShader::OpenGLShader(const class std::basic_string<char,struct std::char_traits<char>,class std::allocator<char> > &)","ph":"X","pid":0,"tid":2665228401,"ts":254137964845},{"cat":"function","dur":6669,"name":"void __cdecl Debut::Renderer2D::Init(void)","ph":"X","pid":0,"tid":2665228401,"ts":254137960291},{"cat":"function","dur":5010,"name":"void __cdecl Debut::ImGuiLayer::OnAttach(void)","ph":"X","pid":0,"tid":2665228401,"ts":254137967045},{"cat":"function","dur":5159,"name":"void __cdecl Debut::LayerStack::PushOverlay(class Debut::Layer *)","ph":"X","pid":0,"tid":2665228401,"ts":254137967041},{"cat":"function","dur":731192,"name":"__cdecl Debut::Application::Application(void)","ph":"X","pid":0,"tid":2665228401,"ts":254137241060},{"cat":"function","dur":52,"name":"void __cdecl Debut::OrthographicCamera::RecalculateViewMatrix(void)","ph":"X","pid":0,"tid":2665228401,"ts":254137972348},{"cat":"function","dur":6980,"name":"OpenGLTexture2D::OpenGLTexture2D(const std::string&)","ph":"X","pid":0,"tid":2665228401,"ts":254137972557},{"cat":"function","dur":8584,"name":"__cdecl Debut::OpenGLTexture2D::OpenGLTexture2D(const class std::basic_string<char,struct std::char_traits<char>,class std::allocator<char> > &)","ph":"X","pid":0,"tid":2665228401,"ts":254137972557},{"cat":"function","dur":8703,"name":"void __cdecl Debut::LayerStack::PushLayer(class Debut::Layer *)","ph":"X","pid":0,"tid":2665228401,"ts":254137972540},{"cat":"function","dur":757407,"name":"App initialization","ph":"X","pid":0,"tid":2665228401,"ts":254137239442}]}