{"otherData": {},"traceEvents":[{"cat":"function","dur":80079,"name":"void __cdecl Debut::OpenGLContext::Init(void)","ph":"X","pid":0,"tid":4088903751,"ts":399944993875},{"cat":"function","dur":192,"name":"void __cdecl Debut::WindowsWindow::SetVSync(bool)","ph":"X","pid":0,"tid":4088903751,"ts":399945076589},{"cat":"function","dur":2302142,"name":"void __cdecl Debut::WindowsWindow::Init(const struct Debut::WindowProps &)","ph":"X","pid":0,"tid":4088903751,"ts":399942774945},{"cat":"function","dur":2569,"name":"__cdecl Debut::OpenGLIndexBuffer::OpenGLIndexBuffer(int *,unsigned int)","ph":"X","pid":0,"tid":4088903751,"ts":399945079269},{"cat":"function","dur":117,"name":"__cdecl Debut::OpenGLVertexBuffer::OpenGLVertexBuffer(unsigned int)","ph":"X","pid":0,"tid":4088903751,"ts":399945082427},{"cat":"function","dur":343,"name":"__cdecl Debut::OpenGLVertexArray::OpenGLVertexArray(void)","ph":"X","pid":0,"tid":4088903751,"ts":399945083261},{"cat":"function","dur":3,"name":"void __cdecl Debut::OpenGLVertexBuffer::Bind(void) const","ph":"X","pid":0,"tid":4088903751,"ts":399945084359},{"cat":"function","dur":2,"name":"void __cdecl Debut::OpenGLIndexBuffer::Bind(void) const","ph":"X","pid":0,"tid":4088903751,"ts":399945084728},{"cat":"function","dur":196,"name":"__cdecl Debut::OpenGLVertexArray::OpenGLVertexArray(void)","ph":"X","pid":0,"tid":4088903751,"ts":399945089901},{"cat":"function","dur":690,"name":"__cdecl Debut::OpenGLVertexBuffer::OpenGLVertexBuffer(unsigned int)","ph":"X","pid":0,"tid":4088903751,"ts":399945090459},{"cat":"function","dur":2,"name":"void __cdecl Debut::OpenGLVertexBuffer::Bind(void) const","ph":"X","pid":0,"tid":4088903751,"ts":399945091752},{"cat":"function","dur":307,"name":"__cdecl Debut::OpenGLTexture2D::OpenGLTexture2D(unsigned int,unsigned int)","ph":"X","pid":0,"tid":4088903751,"ts":399945093935},{"cat":"function","dur":7,"name":"void __cdecl Debut::OpenGLTexture2D::SetData(void *,unsigned int)","ph":"X","pid":0,"tid":4088903751,"ts":399945094780},{"cat":"function","dur":993,"name":"class std::basic_string<char,struct std::char_traits<char>,class std::allocator<char> > __cdecl Debut::OpenGLShader::ReadFile(const class std::basic_string<char,struct std::char_traits<char>,class std::allocator<char> > &)","ph":"X","pid":0,"tid":4088903751,"ts":399945095172},{"cat":"function","dur":550,"name":"class std::unordered_map<unsigned int,class std::basic_string<char,struct std::char_traits<char>,class std::allocator<char> >,struct std::hash<unsigned int>,struct std::equal_to<unsigned int>,class std::allocator<struct std::pair<unsigned int const ,class std::basic_string<char,struct std::char_traits<char>,class std::allocator<char> > > > > __cdecl Debut::OpenGLShader::PreProcess(const class std::basic_string<char,struct std::char_traits<char>,class std::allocator<char> > &)","ph":"X","pid":0,"tid":4088903751,"ts":399945096480},{"cat":"function","dur":5792,"name":"void __cdecl Debut::OpenGLShader::Compile(class std::unordered_map<unsigned int,class std::basic_string<char,struct std::char_traits<char>,class std::allocator<char> >,struct std::hash<unsigned int>,struct std::equal_to<unsigned int>,class std::allocator<struct std::pair<unsigned int const ,class std::basic_string<char,struct std::char_traits<char>,class std::allocator<char> > > > > &)","ph":"X","pid":0,"tid":4088903751,"ts":399945097349},{"cat":"function","dur":1923,"name":"void __cdecl Debut::OpenGLShader::Link(void)","ph":"X","pid":0,"tid":4088903751,"ts":399945103530},{"cat":"function","dur":10758,"name":"__cdecl Debut::OpenGLShader::OpenGLShader(const class std::basic_string<char,struct std::char_traits<char>,class std::allocator<char> > &)","ph":"X","pid":0,"tid":4088903751,"ts":399945095152},{"cat":"function","dur":491,"name":"class std::basic_string<char,struct std::char_traits<char>,class std::allocator<char> > __cdecl Debut::OpenGLShader::ReadFile(const class std::basic_string<char,struct std::char_traits<char>,class std::allocator<char> > &)","ph":"X","pid":0,"tid":4088903751,"ts":399945106198},{"cat":"function","dur":133,"name":"class std::unordered_map<unsigned int,class std::basic_string<char,struct std::char_traits<char>,class std::allocator<char> >,struct std::hash<unsigned int>,struct std::equal_to<unsigned int>,class std::allocator<struct std::pair<unsigned int const ,class std::basic_string<char,struct std::char_traits<char>,class std::allocator<char> > > > > __cdecl Debut::OpenGLShader::PreProcess(const class std::basic_string<char,struct std::char_traits<char>,class std::allocator<char> > &)","ph":"X","pid":0,"tid":4088903751,"ts":399945106937},{"cat":"function","dur":1026,"name":"void __cdecl Debut::OpenGLShader::Compile(class std::unordered_map<unsigned int,class std::basic_string<char,struct std::char_traits<char>,class std::allocator<char> >,struct std::hash<unsigned int>,struct std::equal_to<unsigned int>,class std::allocator<struct std::pair<unsigned int const ,class std::basic_string<char,struct std::char_traits<char>,class std::allocator<char> > > > > &)","ph":"X","pid":0,"tid":4088903751,"ts":399945107450},{"cat":"function","dur":726,"name":"void __cdecl Debut::OpenGLShader::Link(void)","ph":"X","pid":0,"tid":4088903751,"ts":399945108800},{"cat":"function","dur":3616,"name":"__cdecl Debut::OpenGLShader::OpenGLShader(const class std::basic_string<char,struct std::char_traits<char>,class std::allocator<char> > &)","ph":"X","pid":0,"tid":4088903751,"ts":399945106197},{"cat":"function","dur":264,"name":"void __cdecl Debut::OpenGLShader::Bind(void) const","ph":"X","pid":0,"tid":4088903751,"ts":399945110011},{"cat":"function","dur":33006,"name":"void __cdecl Debut::Renderer2D::Init(void)","ph":"X","pid":0,"tid":4088903751,"ts":399945077789},{"cat":"function","dur":16845,"name":"void __cdecl Debut::ImGuiLayer::OnAttach(void)","ph":"X","pid":0,"tid":4088903751,"ts":399945111061},{"cat":"function","dur":17276,"name":"void __cdecl Debut::LayerStack::PushOverlay(class Debut::Layer *)","ph":"X","pid":0,"tid":4088903751,"ts":399945111027},{"cat":"function","dur":2354303,"name":"__cdecl Debut::Application::Application(const class std::basic_string<char,struct std::char_traits<char>,class std::allocator<char> > &)","ph":"X","pid":0,"tid":4088903751,"ts":399942774186},{"cat":"function","dur":400,"name":"__cdecl Debut::OpenGLTexture2D::OpenGLTexture2D(unsigned int,unsigned int)","ph":"X","pid":0,"tid":4088903751,"ts":399945128799},{"cat":"function","dur":53129,"name":"OpenGLTexture2D::OpenGLTexture2D(const std::string&)","ph":"X","pid":0,"tid":4088903751,"ts":399945150789},{"cat":"function","dur":65679,"name":"__cdecl Debut::OpenGLTexture2D::OpenGLTexture2D(const class std::basic_string<char,struct std::char_traits<char>,class std::allocator<char> > &,struct Debut::Texture2DConfig)","ph":"X","pid":0,"tid":4088903751,"ts":399945150766},{"cat":"function","dur":25403,"name":"OpenGLTexture2D::OpenGLTexture2D(const std::string&)","ph":"X","pid":0,"tid":4088903751,"ts":399945219725},{"cat":"function","dur":32785,"name":"__cdecl Debut::OpenGLTexture2D::OpenGLTexture2D(const class std::basic_string<char,struct std::char_traits<char>,class std::allocator<char> > &,struct Debut::Texture2DConfig)","ph":"X","pid":0,"tid":4088903751,"ts":399945219722},{"cat":"function","dur":733,"name":"OpenGLTexture2D::OpenGLTexture2D(const std::string&)","ph":"X","pid":0,"tid":4088903751,"ts":399945288658},{"cat":"function","dur":3913,"name":"__cdecl Debut::OpenGLTexture2D::OpenGLTexture2D(const class std::basic_string<char,struct std::char_traits<char>,class std::allocator<char> > &,struct Debut::Texture2DConfig)","ph":"X","pid":0,"tid":4088903751,"ts":399945288657},{"cat":"function","dur":551,"name":"OpenGLTexture2D::OpenGLTexture2D(const std::string&)","ph":"X","pid":0,"tid":4088903751,"ts":399945297723},{"cat":"function","dur":1771,"name":"__cdecl Debut::OpenGLTexture2D::OpenGLTexture2D(const class std::basic_string<char,struct std::char_traits<char>,class std::allocator<char> > &,struct Debut::Texture2DConfig)","ph":"X","pid":0,"tid":4088903751,"ts":399945297722},{"cat":"function","dur":68066,"name":"void __cdecl Debut::LayerStack::PushLayer(class Debut::Layer *)","ph":"X","pid":0,"tid":4088903751,"ts":399945253141},{"cat":"function","dur":2581478,"name":"App initialization","ph":"X","pid":0,"tid":4088903751,"ts":399942768945}]}